mongo_schema/__init__.py
mongo_schema-1.0.0.post0.dist-info/LICENSE
mongo_schema-1.0.0.post0.dist-info/METADATA
mongo_schema-1.0.0.post0.dist-info/WHEEL
mongo_schema-1.0.0.post0.dist-info/top_level.txt
mongo_schema-1.0.0.post0.dist-info/RECORD
