Metadata-Version: 2.1
Name: mongo-schema
Version: 1.0.0.post0
Summary: Schema validator for MongoDB's JSON Schema variant
Home-page: https://gitlab.com/embray/mongo-schema/
Author: E. Madison Bray
Author-email: embray@lri.fr
License: BSD
Platform: UNKNOWN
Classifier: Development Status :: 5 - Production/Stable
Classifier: License :: OSI Approved :: BSD License
Classifier: Programming Language :: Python :: 3.6
Classifier: Programming Language :: Python :: 3.7
Classifier: Programming Language :: Python :: 3.8
Classifier: Programming Language :: Python :: 3.9
Classifier: Programming Language :: Python :: 3.10
Requires-Python: >=3.6
Requires-Dist: jsonschema
Provides-Extra: tests
Requires-Dist: flake8 ; extra == 'tests'
Requires-Dist: pytest ; extra == 'tests'
Requires-Dist: pytest-cov ; extra == 'tests'
Requires-Dist: pymongo (>=3.6) ; extra == 'tests'
